imad/__init__.py
imad-0.2.dist-info/METADATA
imad-0.2.dist-info/WHEEL
imad-0.2.dist-info/top_level.txt
imad-0.2.dist-info/RECORD
