Metadata-Version: 2.1
Name: imad
Version: 0.2
Summary: My Amazing Project
Home-page: UNKNOWN
Author: TechIO
License: UNKNOWN
Platform: UNKNOWN
Requires-Dist: tk
